Workbook

Sheet Gastos
A1: Gastos de la idea final | G1: Total con IVA en dólares | I1: =I24 -> 22557.403
G2: Total con IVA en pesos | I2: =I25 -> 151847
A4: Ítem | B4: Proveedor | C4: Cantidad | D4: Unidad | E4: Precio unitario | F4: Moneda | G4: ¿Incluye IVA? | H4: Subtotal | I4: Total con IVA
A5: Lona mesh 41 × 24,5 m, costura electrónica, ojales cada 50 cm | B5: Romela Toldos | C5: =1 -> 1 | D5: lona | E5: 14650 | F5: USD | G5: No | H5: =C5*E5 -> 14650 | I5: =IF(G5="No",H5*(1+Supuestos!$B$5),H5) -> 17873
A6: Postes: caño redondo 6" × 3 mm, barra de 6 m | B6: Appelsa | C6: =Supuestos!$B$6/3*Supuestos!$B$8+Supuestos!$B$9 -> 18 | D6: barra | E6: 112.29 | F6: USD | G6: No | H6: =C6*E6 -> 2021.22 | I6: =IF(G6="No",H6*(1+Supuestos!$B$5),H6) -> 2465.8884
A7: Vainas: tubo cuadrado 200 × 200 × 4,75 mm, barra de 6 m | B7: Appelsa | C7: =ROUNDUP(Supuestos!$B$6/INT(6/Supuestos!$B$10),0) -> 3 | D7: barra | E7: 312.14 | F7: USD | G7: No | H7: =C7*E7 -> 936.42 | I7: =IF(G7="No",H7*(1+Supuestos!$B$5),H7) -> 1142.4324
A8: Empalmes interiores de los postes: caño redondo 5" × 3 mm, barra de 6 m | B8: Appelsa | C8: =ROUNDUP(Supuestos!$B$6*Supuestos!$B$11/6,0) -> 2 | D8: barra | E8: 94.11 | F8: USD | G8: No | H8: =C8*E8 -> 188.22 | I8: =IF(G8="No",H8*(1+Supuestos!$B$5),H8) -> 229.6284
A9: Tapas de las vainas: chapa negra N.º 12, 1,50 × 3 m | B9: Appelsa | C9: =1 -> 1 | D9: chapa | E9: 140.81 | F9: USD | G9: No | H9: =C9*E9 -> 140.81 | I9: =IF(G9="No",H9*(1+Supuestos!$B$5),H9) -> 171.7882
A10: Placas de anclaje en paredes y cabezales: planchuela 5/8" × 5", barra de 6 m | B10: Appelsa | C10: =ROUNDUP((Supuestos!$B$12*Supuestos!$B$13+Supuestos!$B$6*Supuestos!$B$14)/6,0) -> 1 | D10: barra | E10: 140.07 | F10: USD | G10: No | H10: =C10*E10 -> 140.07 | I10: =IF(G10="No",H10*(1+Supuestos!$B$5),H10) -> 170.8854
A11: Cable de acero galvanizado 16 mm (cables principales) | B11: Bianchi | C11: =Supuestos!$B$15*Supuestos!$B$16 -> 215 | D11: m | E11: 495 | F11: UYU | G11: Sí | H11: =C11*E11 -> 106425 | I11: =IF(G11="No",H11*(1+Supuestos!$B$5),H11) -> 106425
A12: Cable de acero galvanizado 12 mm (tensores del borde sur) | B12: Bianchi | C12: =Supuestos!$B$17*Supuestos!$B$18 -> 27 | D12: m | E12: 285 | F12: UYU | G12: Sí | H12: =C12*E12 -> 7695 | I12: =IF(G12="No",H12*(1+Supuestos!$B$5),H12) -> 7695
A13: Grillete certificado 7/8" (6,5 t) | B13: Bianchi | C13: =Supuestos!$B$15*2 -> 10 | D13: u | E13: 40.43 | F13: USD | G13: Sí | H13: =C13*E13 -> 404.3 | I13: =IF(G13="No",H13*(1+Supuestos!$B$5),H13) -> 404.3
A14: Grillete certificado 5/8" (3,25 t) | B14: Bianchi | C14: =Supuestos!$B$17*2 -> 6 | D14: u | E14: 16.58 | F14: USD | G14: Sí | H14: =C14*E14 -> 99.48 | I14: =IF(G14="No",H14*(1+Supuestos!$B$5),H14) -> 99.48
A15: Tensor ojo y gancho 22 mm (cables principales) | B15: Bianchi | C15: =Supuestos!$B$15 -> 5 | D15: u | E15: 1165 | F15: UYU | G15: Sí | H15: =C15*E15 -> 5825 | I15: =IF(G15="No",H15*(1+Supuestos!$B$5),H15) -> 5825
A16: Tensor ojo y gancho 16 mm (tensores sur) | B16: Bianchi | C16: =Supuestos!$B$17 -> 3 | D16: u | E16: 506 | F16: UYU | G16: Sí | H16: =C16*E16 -> 1518 | I16: =IF(G16="No",H16*(1+Supuestos!$B$5),H16) -> 1518
A17: Apretacable para cable de 16 mm | B17: Bianchi | C17: =Supuestos!$B$15*2*Supuestos!$B$19 -> 30 | D17: u | E17: 137 | F17: UYU | G17: Sí | H17: =C17*E17 -> 4110 | I17: =IF(G17="No",H17*(1+Supuestos!$B$5),H17) -> 4110
A18: Apretacable para cable de 12 mm | B18: Bianchi | C18: =Supuestos!$B$17*2*Supuestos!$B$19 -> 18 | D18: u | E18: 96 | F18: UYU | G18: Sí | H18: =C18*E18 -> 1728 | I18: =IF(G18="No",H18*(1+Supuestos!$B$5),H18) -> 1728
A19: Adhesivo para anclajes químicos Anchofrix 300 ml | B19: Sodimac | C19: =ROUNDUP(Supuestos!$B$12*Supuestos!$B$20/Supuestos!$B$21,0) -> 4 | D19: u | E19: 1696 | F19: UYU | G19: Sí | H19: =C19*E19 -> 6784 | I19: =IF(G19="No",H19*(1+Supuestos!$B$5),H19) -> 6784
A20: Varilla roscada zincada 1/2" × 1 m | B20: Sodimac | C20: =ROUNDUP(Supuestos!$B$12*Supuestos!$B$20*Supuestos!$B$22,0)+ROUNDUP(Supuestos!$B$6/Supuestos!$B$23,0) -> 14 | D20: u | E20: 169 | F20: UYU | G20: Sí | H20: =C20*E20 -> 2366 | I20: =IF(G20="No",H20*(1+Supuestos!$B$5),H20) -> 2366
A21: Arandela plana 1/2" (paquete de 20) | B21: Sodimac | C21: =ROUNDUP((Supuestos!$B$12*Supuestos!$B$20+Supuestos!$B$6*2)/20,0) -> 4 | D21: paquete | E21: 249 | F21: UYU | G21: Sí | H21: =C21*E21 -> 996 | I21: =IF(G21="No",H21*(1+Supuestos!$B$5),H21) -> 996
A22: Cuerda náutica de poliéster 8 mm, 100 m | B22: Polietileno Obelisco | C22: =ROUNDUP(Supuestos!$B$24*Supuestos!$B$25/100,0) -> 6 | D22: rollo | E22: 2400 | F22: UYU | G22: Sí | H22: =C22*E22 -> 14400 | I22: =IF(G22="No",H22*(1+Supuestos!$B$5),H22) -> 14400
A24: Total en dólares | F24: USD | H24: =SUMIF($F$5:$F$22,"USD",H$5:H$22) -> 18580.52 | I24: =SUMIF($F$5:$F$22,"USD",I$5:I$22) -> 22557.403
A25: Total en pesos | F25: UYU | H25: =SUMIF($F$5:$F$22,"UYU",H$5:H$22) -> 151847 | I25: =SUMIF($F$5:$F$22,"UYU",I$5:I$22) -> 151847
A27: No incluye mano de obra, hormigón (habría que perforar el piso del colegio), ingeniero estructural, galvanizado ni equipo de elevación. Ver la hoja Observaciones.
A28: Las filas celestes están en dólares y las blancas en pesos. Los totales no se suman entre sí porque no se usa tipo de cambio.
A29: Las cantidades salen de la hoja Supuestos: si se cambia un dato ahí, esta hoja se recalcula.

Sheet Gastos expandido
A1: Gastos expandido
A2: Proveedor, precio, cantidad y link de cada ítem de la idea final. Precios al 1/10/2026.
A4: Item | B4: Proveedor | C4: Costo | D4: Con IVA? | E4: Cantidad | F4: Coste total | G4: Comentarios | H4: Link
A5: Lona mesh 41 × 24,5 m, costura electrónica, ojales cada 50 cm | B5: Romela Toldos | C5: 14650 | D5: No | E5: =1 -> 1 | F5: =C5*E5 -> 14650 | G5: Cotización por WhatsApp (099 664 452). Una sola pieza a medida. | H5: https://www.toldosromela.com.uy/
A6: Postes: caño redondo 6" × 3 mm, barra de 6 m | B6: Appelsa | C6: 112.29 | D6: No | E6: =Supuestos!$B$6/3*Supuestos!$B$8+Supuestos!$B$9 -> 18 | F6: =C6*E6 -> 2021.22 | G6: Precio por unidad, en dólares, más IVA. Unos 72 kg por barra. Consultar si viene galvanizado. | H6: https://www.appelsa.com.uy/product-page/6-x-3mm-11-97kg
A7: Vainas: tubo cuadrado 200 × 200 × 4,75 mm, barra de 6 m | B7: Appelsa | C7: 312.14 | D7: No | E7: =ROUNDUP(Supuestos!$B$6/INT(6/Supuestos!$B$10),0) -> 3 | F7: =C7*E7 -> 936.42 | G7: De cada barra salen 4 vainas de 1,3 m. Deja holgura alrededor del poste de 6". | H7: https://www.appelsa.com.uy/product-page/200-x-200-x-4-75mm-30-11kg
A8: Empalmes interiores de los postes: caño redondo 5" × 3 mm, barra de 6 m | B8: Appelsa | C8: 94.11 | D8: No | E8: =ROUNDUP(Supuestos!$B$6*Supuestos!$B$11/6,0) -> 2 | F8: =C8*E8 -> 188.22 | G8: Une el tramo de 6 m con el de 2 m de cada poste. El largo y la fijación los define el ingeniero. | H8: https://www.appelsa.com.uy/product-page/5-x-3mm-9-500kg
A9: Placas de anclaje en paredes y cabezales: planchuela 5/8" × 5", barra de 6 m | B9: Appelsa | C9: 140.07 | D9: No | E9: =ROUNDUP((Supuestos!$B$12*Supuestos!$B$13+Supuestos!$B$6*Supuestos!$B$14)/6,0) -> 1 | F9: =C9*E9 -> 140.07 | G9: 10 placas de 0,3 m + 12 cabezales de 0,2 m = 5,4 m. | H9: https://www.appelsa.com.uy/product-page/5-8-x-5-96-6kg
A10: Cable de acero galvanizado 16 mm (cables principales) | B10: Bianchi | C10: 495 | D10: Sí | E10: =Supuestos!$B$15*Supuestos!$B$16 -> 215 | F10: =C10*E10 -> 106425 | G10: Alma de cáñamo. La página no publica la carga de rotura: el ingeniero puede pedir alma de acero o más diámetro. | H10: https://www.bianchi.com.uy/cable-acero-16mmalma-canamo
A11: Cable de acero galvanizado 12 mm (tensores del borde sur) | B11: Bianchi | C11: 285 | D11: Sí | E11: =Supuestos!$B$17*Supuestos!$B$18 -> 27 | F11: =C11*E11 -> 7695 | G11: Alma de cáñamo. Del tope de cada poste sur a un bloque en el piso. | H11: https://www.bianchi.com.uy/cable-acero-12mmalma-canamo
A12: Grillete certificado 7/8" (6,5 t) | B12: Bianchi | C12: 40.43 | D12: Sí | E12: =Supuestos!$B$15*2 -> 10 | F12: =C12*E12 -> 404.3 | G12: Certificado ABLE, carga de trabajo 6,5 t (mayor que las 5,6 t por cable). 2 por cable. | H12: https://www.bianchi.com.uy/grillete-alta-resistencia-78-pulga-65ton-certificados-able
A13: Grillete certificado 5/8" (3,25 t) | B13: Bianchi | C13: 16.58 | D13: Sí | E13: =Supuestos!$B$17*2 -> 6 | F13: =C13*E13 -> 99.48 | G13: Para los tensores del borde sur. 2 por tensor. | H13: https://www.bianchi.com.uy/grillete-alta-resistencia-58-pulg-325ton-certificados-able
A14: Tensor ojo y gancho 22 mm (cables principales) | B14: Bianchi | C14: 1165 | D14: Sí | E14: =Supuestos!$B$15 -> 5 | F14: =C14*E14 -> 5825 | G14: Para tensar cada cable. No publica carga de trabajo: el ingeniero puede pedir tensores certificados ojo-ojo. | H14: https://www.bianchi.com.uy/tensor-ojo-y-gancho-22mm
A15: Tensor ojo y gancho 16 mm (tensores sur) | B15: Bianchi | C15: 506 | D15: Sí | E15: =Supuestos!$B$17 -> 3 | F15: =C15*E15 -> 1518 | G15: Uno por tensor del borde sur. No publica carga de trabajo. | H15: https://www.bianchi.com.uy/tensor-ojo-y-gancho-16mm
A16: Apretacable para cable de 16 mm | B16: Bianchi | C16: 137 | D16: Sí | E16: =Supuestos!$B$15*2*Supuestos!$B$19 -> 30 | F16: =C16*E16 -> 4110 | G16: 3 por extremo de cable, 2 extremos por cable. | H16: https://www.bianchi.com.uy/apretacable-para-cable-de-acero-16-mm
A17: Apretacable para cable de 12 mm | B17: Bianchi | C17: 96 | D17: Sí | E17: =Supuestos!$B$17*2*Supuestos!$B$19 -> 18 | F17: =C17*E17 -> 1728 | G17: 3 por extremo, 2 extremos por tensor sur. | H17: https://www.bianchi.com.uy/apretacable-para-cable-de-acero-12-mm
A18: Adhesivo para anclajes químicos Anchofrix 300 ml | B18: Sodimac | C18: 1696 | D18: Sí | E18: =ROUNDUP(Supuestos!$B$12*Supuestos!$B$20/Supuestos!$B$21,0) -> 4 | F18: =C18*E18 -> 6784 | G18: Para fijar las varillas de las placas en las paredes. | H18: https://www.sodimac.com.uy/sodimac-uy/product/1898396/
A19: Varilla roscada zincada 1/2" × 1 m | B19: Sodimac | C19: 169 | D19: Sí | E19: =ROUNDUP(Supuestos!$B$12*Supuestos!$B$20*Supuestos!$B$22,0)+ROUNDUP(Supuestos!$B$6/Supuestos!$B$23,0) -> 14 | F19: =C19*E19 -> 2366 | G19: Anclajes de las placas (40 × 0,25 m) y pasadores de los postes (12). | H19: https://www.sodimac.com.uy/sodimac-uy/product/3254011/
A20: Arandela plana 1/2" (paquete de 20) | B20: Sodimac | C20: 249 | D20: Sí | E20: =ROUNDUP((Supuestos!$B$12*Supuestos!$B$20+Supuestos!$B$6*2)/20,0) -> 4 | F20: =C20*E20 -> 996 | G20: Para anclajes y pasadores. | H20: https://www.sodimac.com.uy/sodimac-uy/product/1982427/
A21: Cuerda náutica de poliéster 8 mm, 100 m | B21: Polietileno Obelisco | C21: 2400 | D21: Sí | E21: =ROUNDUP(Supuestos!$B$24*Supuestos!$B$25/100,0) -> 6 | F21: =C21*E21 -> 14400 | G21: Para atar la lona a los cables, ojal por ojal. Lista de junio 2025; puede variar un 10 %. | H21: https://www.nylon.com.uy/
A23: Coste total = costo unitario × cantidad, con o sin IVA según la columna "Con IVA?". Excluye mano de obra.

Sheet Supuestos
A1: Supuestos
A2: Datos que se usan para calcular las otras hojas. Los valores en azul se pueden cambiar y todo se recalcula.
A4: Concepto | B4: Valor | C4: Unidad | D4: De dónde sale
A5: IVA básico de Uruguay | B5: 0.22 | C5: % | D5: Tasa básica de IVA en Uruguay.
A6: Cantidad de postes | B6: 12 | C6: u | D6: Recomendacion_postes_Idea2.docx: 3 filas de 4 postes.
A7: Largo de cada poste | B7: 8 | C7: m | D7: 7 m sobre el piso + 1 m dentro de la vaina; se arma en tramos de 6 m + 2 m.
A8: Barras de 6 m cada 3 postes | B8: 4 | C8: u | D8: 3 barras enteras para los tramos de 6 m + 1 barra cortada en 3 tramos de 2 m.
A9: Barras de reserva (cortes y errores) | B9: 2 | C9: u | D9: Margen propio.
A10: Largo de cada vaina | B10: 1.3 | C10: m | D10: El poste entra 1 m; 0,3 m para el fondo con drenaje.
A11: Largo de cada empalme interior | B11: 0.6 | C11: m | D11: 0,3 m dentro de cada tramo del poste. Lo define el ingeniero.
A12: Placas de anclaje en paredes | B12: 10 | C12: u | D12: 5 cables × 2 paredes (este y oeste).
A13: Largo de cada placa de anclaje | B13: 0.3 | C13: m | D13: Supuesto para 4 anclajes por placa.
A14: Largo de cada cabezal (punta del poste) | B14: 0.2 | C14: m | D14: Pieza de apoyo del cable.
A15: Cables principales este-oeste | B15: 5 | C15: u | D15: Recomendacion_postes_Idea2.docx.
A16: Largo de cada cable principal | B16: 43 | C16: m | D16: 40,9 m de pared a pared + unos 2 m para terminaciones.
... A25: Cuerda por ojal | B25: 1 | C25: m | D25: Estimación propia.
A26: Superficie de la lona | B26: =41*24.5 -> 1004.5 | C26: m² | D26: Lona de 41 × 24,5 m (cotización de Romela).
A27: Superficie de un paño de Polientile | B27: =1*4.2 -> 4.2 | C27: m² | D27: Cotización de Polientile: paño de 1 × 4,20 m (dato del equipo).
A29: Otros supuestos (sin número)
A30: • Precios leídos de las páginas de cada proveedor el 1/10/2026. Hay que confirmarlos al comprar.
A31: • Appelsa publica en dólares, por unidad y SIN IVA (lo dice su página). Se le suma el IVA de la celda B5.
A32: • Sodimac, Barraca Julia y Polietileno Obelisco: precios al público CON IVA incluido.
A33: • Bianchi: la página no aclara el IVA; se toma como precio al público con IVA incluido. Confirmar.
A34: • Cable de 16 mm y de 12 mm de Bianchi: la página no dice la unidad; se toma como precio por metro (el de 5 mm dice "por metro"). Confirmar.
A35: • Diámetro exterior del caño de 6" de Appelsa: unos 165 mm (deducido de 11,97 kg/m con 3 mm de pared). Por eso la vaina es el tubo de 200 × 200 mm: el de 180 × 180 deja muy poca holgura.
A36: • Cargas de diseño (de Recomendacion_postes_Idea2.docx): viento de 0,35 kN/m² y hasta 5,6 t por cable principal.
A37: • Dólares y pesos se suman por separado: no se usa tipo de cambio.

Sheet Observaciones
A1: Observaciones
A2: Datos relevantes que no entran en los totales.
A4: No incluido en los gastos
A5: Mano de obra | B5: No se incluye en ningún cálculo: armado, montaje, soldadura y cortes quedan fuera.
A6: Hormigón | B6: No se incluye porque habría que perforar el piso del colegio y usar ese material. Serían 12 bases de unos 1,4 m³ (cerca de 17 m³) y 3 bloques para los tensores del borde sur.
A7: Ingeniero estructural | B7: Tiene que verificar y firmar el cálculo: viento, cables, anclajes, vainas, empalmes y bases.
A8: Galvanizado en caliente | B8: Tubacero lo hace a terceros (Coronel Raíz 949, tel. 2354 3300), pero no publica precio.
A9: Plataforma elevadora o grúa | B9: Hace falta para trabajar a 7 m y parar postes de unos 96 kg. Sin precio publicado.
A10: Guardacabos 16 mm y tuercas 1/2" | B10: No encontramos precio online. Comprarlos junto con el resto de la ferretería.
A12: Avisos técnicos
A13: Cables y tensores | B13: El cable de 16 mm (alma de cáñamo) y los tensores con gancho no publican su carga de trabajo. El ingeniero puede pedir cable de alma de acero, más diámetro o tensores certificados ojo-ojo.
A14: Caño de Appelsa | B14: La página no aclara si el caño es galvanizado o negro. Si es negro, hay que galvanizarlo o protegerlo.
A15: Cotizaciones propias | B15: Romela Toldos, Polientile y Nico están en la carpeta Cotizaciones del proyecto.
A16: Techo de Nico | B16: Su cotización ("muy por arriba de 50 dólares por m²") era para un techo de chapa con estructura metálica, no para esta idea; por eso no figura como proveedor.
A18: Poste desmontable
A19: Vaina enterrada con tapa a ras del piso (izquierda) y poste montado con la malla (derecha). Esquema sin escala.
